 {
   "departamentos": [
	    
	    {"id":0,"departamento":"Amazonas","provincias":[
	                                     {"id":0,"provincia":"Chachapoyas","distritos":[
	                                                                {"id":0,"distrito":"Chachapoyas"},
	                                                                {"id":1,"distrito":"Asunción"},
	                                                                {"id":2,"distrito":"Balsas"},
	                                                                {"id":3,"distrito":"Cheto"},
	                                                                {"id":4,"distrito":"Chiliquin"},
	                                                                {"id":5,"distrito":"Chuquibamba"},
	                                                                {"id":6,"distrito":"Granada"},
	                                                                {"id":7,"distrito":"Huancas"},
	                                                                {"id":8,"distrito":"La Jalca"},
	                                                                {"id":9,"distrito":"Leimebamba"},
	                                                                {"id":10,"distrito":"Levanto"},
	                                                                {"id":11,"distrito":"Magdalena"},
	                                                                {"id":12,"distrito":"Mariscal Castilla"},
	                                                                {"id":13,"distrito":"Molinopampa"},
	                                                                {"id":14,"distrito":"Montevideo"},
	                                                                {"id":15,"distrito":"Olleros"},
	                                                                {"id":16,"distrito":"Quinjalca"},
	                                                                {"id":17,"distrito":"San Francisco de Daguas"},
	                                                                {"id":18,"distrito":"San Isidro de Maino"},
	                                                                {"id":19,"distrito":"Soloco"},
	                                                                {"id":20,"distrito":"Sonche"}
	                                     ]},
	                                     {"id":1,"provincia":"Bagua","distritos":[
	                                                                {"id":0,"distrito":"Bagua"},
	                                                                {"id":1,"distrito":"Aramango"},
	                                                                {"id":2,"distrito":"El Parco"},
	                                                                {"id":3,"distrito":"Imaza"},
	                                                                {"id":4,"distrito":"Chiliquin"},
	                                                                {"id":5,"distrito":"La Peca"}
	                                     ]},
	                                     {"id":2,"provincia":"Bongará","distritos":[
	                                                                {"id":0,"distrito":"Jumbilla"},
	                                                                {"id":1,"distrito":"Chisquilla"},
	                                                                {"id":2,"distrito":"Churuja"},
	                                                                {"id":3,"distrito":"Corosha"},
	                                                                {"id":4,"distrito":"Cuispes"},
	                                                                {"id":5,"distrito":"Florida"},
	                                                                {"id":6,"distrito":"Jazan"},
	                                                                {"id":7,"distrito":"Recta"},
	                                                                {"id":8,"distrito":"San Carlos"},
	                                                                {"id":9,"distrito":"Shipasbamba"},
	                                                                {"id":10,"distrito":"Valera"},
	                                                                {"id":11,"distrito":"Yambrasbamba"}
	                                     ]},
	                                     {"id":3,"provincia":"Condorcanqui","distritos":[
	                                                                {"id":0,"distrito":"Nieva"},
	                                                                {"id":1,"distrito":"El Cenepa"},
	                                                                {"id":2,"distrito":"Río Santiago"}
	                                     ]},
	                                     {"id":4,"provincia":"Luya","distritos":[
	                                                                {"id":0,"distrito":"Lamud"},
	                                                                {"id":1,"distrito":"Camporredondo"},
	                                                                {"id":2,"distrito":"Cocabamba"},
	                                                                {"id":3,"distrito":"Colcamar"},
	                                                                {"id":4,"distrito":"Conila"},
	                                                                {"id":5,"distrito":"Inguilpata"},
	                                                                {"id":6,"distrito":"Longuita"},
	                                                                {"id":7,"distrito":"Lonya Chico"},
	                                                                {"id":8,"distrito":"Luya"},
	                                                                {"id":9,"distrito":"Luya Viejo"},
	                                                                {"id":10,"distrito":"María"},
	                                                                {"id":11,"distrito":"Ocalli"},
	                                                                {"id":12,"distrito":"Ocumal"},
	                                                                {"id":13,"distrito":"Pisuquia"},
	                                                                {"id":14,"distrito":"Providencia"},
	                                                                {"id":15,"distrito":"San Cristóbal"},
	                                                                {"id":16,"distrito":"San Francisco de Yeso"},
	                                                                {"id":17,"distrito":"San Jerónimo"},
	                                                                {"id":18,"distrito":"San Juan de Lopecancha"},
	                                                                {"id":19,"distrito":"Santa Catalina"},
	                                                                {"id":20,"distrito":"Santo Tomas"},
	                                                                {"id":21,"distrito":"Tingo"},
	                                                                {"id":22,"distrito":"Trita"}
	                                     ]},
	                                     {"id":5,"provincia":"Rodríguez de Mendoza","distritos":[
	                                                                {"id":0,"distrito":"San Nicolás"},
	                                                                {"id":1,"distrito":"Chirimoto"},
	                                                                {"id":2,"distrito":"Cochamal"},
	                                                                {"id":3,"distrito":"Huambo"},
	                                                                {"id":4,"distrito":"Limabamba"},
	                                                                {"id":5,"distrito":"Longar"},
	                                                                {"id":6,"distrito":"Mariscal Benavides"},
	                                                                {"id":7,"distrito":"Milpuc"},
	                                                                {"id":8,"distrito":"Omia"},
	                                                                {"id":9,"distrito":"Santa Rosa"},
	                                                                {"id":10,"distrito":"Totora"},
	                                                                {"id":11,"distrito":"Vista Alegre"}
	                                     ]},
	                                     {"id":6,"provincia":"Utcubamba","distritos":[
	                                                                {"id":0,"distrito":"Bagua Grande"},
	                                                                {"id":1,"distrito":"Cajaruro"},
	                                                                {"id":2,"distrito":"Cumba"},
	                                                                {"id":3,"distrito":"El Milagro"},
	                                                                {"id":4,"distrito":"Jamalca"},
	                                                                {"id":5,"distrito":"Lonya Grande"},
	                                                                {"id":6,"distrito":"Yamon"}
	                                     ]}
	    ]},
	    {"id":1,"departamento":"Áncash","provincias":[
	                                     {"id":0,"provincia":"Huaraz","distritos":[
	                                                                {"id":0,"distrito":"Huaraz"},
	                                                                {"id":1,"distrito":"Cochabamba"},
	                                                                {"id":2,"distrito":"Colcabamba"},
	                                                                {"id":3,"distrito":"Huanchay"},
	                                                                {"id":4,"distrito":"Independencia"},
	                                                                {"id":5,"distrito":"Jangas"},
	                                                                {"id":6,"distrito":"La Libertad"},
	                                                                {"id":7,"distrito":"Olleros"},
	                                                                {"id":8,"distrito":"Pampas Grande"},
	                                                                {"id":9,"distrito":"Pariacoto"},
	                                                                {"id":10,"distrito":"Pira"},
	                                                                {"id":11,"distrito":"Tarica"}
	                                     ]},
	                                     {"id":1,"provincia":"Aija","distritos":[
	                                                                {"id":0,"distrito":"Aija"},
	                                                                {"id":1,"distrito":"Coris"},
	                                                                {"id":2,"distrito":"Huacllan"},
	                                                                {"id":3,"distrito":"La Merced"},
	                                                                {"id":4,"distrito":"Succha"}
	                                     ]},
	                                     {"id":2,"provincia":"Antonio Raymondi","distritos":[
	                                                                {"id":0,"distrito":"Llamellin"},
	                                                                {"id":1,"distrito":"Aczo"},
	                                                                {"id":2,"distrito":"Chaccho"},
	                                                                {"id":3,"distrito":"Chingas"},
	                                                                {"id":4,"distrito":"Mirgas"},
	                                                                {"id":5,"distrito":"San Juan de Rontoy"}
	                                     ]},
	                                     {"id":3,"provincia":"Asunción","distritos":[
	                                                                {"id":0,"distrito":"Chacas"},
	                                                                {"id":1,"distrito":"Acochaca"}
	                                     ]},
	                                     {"id":4,"provincia":"Bolognesi","distritos":[
	                                                                {"id":0,"distrito":"Chiquian"},
	                                                                {"id":1,"distrito":"Abelardo Pardo Lezameta"},
	                                                                {"id":2,"distrito":"Antonio Raymondi"},
	                                                                {"id":3,"distrito":"Aquia"},
	                                                                {"id":4,"distrito":"Cajacay"},
	                                                                {"id":5,"distrito":"Canis"},
	                                                                {"id":6,"distrito":"Colquioc"},
	                                                                {"id":7,"distrito":"Huallanca"},
	                                                                {"id":8,"distrito":"Huasta"},
	                                                                {"id":9,"distrito":"Huayllacayan"},
	                                                                {"id":10,"distrito":"La Primavera"},
	                                                                {"id":11,"distrito":"Mangas"},
	                                                                {"id":12,"distrito":"Pacllon"},
	                                                                {"id":13,"distrito":"San Miguel de Corpanqui"},
	                                                                {"id":14,"distrito":"Ticllos"}
	                                     ]},
	                                     {"id":5,"provincia":"Carhuaz","distritos":[
	                                                                {"id":0,"distrito":"Carhuaz"},
	                                                                {"id":1,"distrito":"Acopampa"},
	                                                                {"id":2,"distrito":"Amashca"},
	                                                                {"id":3,"distrito":"Anta"},
	                                                                {"id":4,"distrito":"Ataquero"},
	                                                                {"id":5,"distrito":"Marcara"},
	                                                                {"id":6,"distrito":"Pariahuanca"},
	                                                                {"id":7,"distrito":"San Miguel de Aco"},
	                                                                {"id":8,"distrito":"Shilla"},
	                                                                {"id":9,"distrito":"Tinco"},
	                                                                {"id":10,"distrito":"Yungar"}
	                                     ]},
	                                     {"id":6,"provincia":"Carlos Fermín Fitzcarrald","distritos":[
	                                                                {"id":0,"distrito":"San Luis"},
	                                                                {"id":1,"distrito":"San Nicolás"},
	                                                                {"id":2,"distrito":"Yauya"}
	                                     ]},
	                                     {"id":7,"provincia":"Casma","distritos":[
	                                                                {"id":0,"distrito":"Casma"},
	                                                                {"id":1,"distrito":"Buena Vista Alta"},
	                                                                {"id":2,"distrito":"Comandante Noel"},
	                                                                {"id":3,"distrito":"Yautan"}
	                                     ]},
	                                     {"id":8,"provincia":"Corongo","distritos":[
	                                                                {"id":0,"distrito":"Corongo"},
	                                                                {"id":1,"distrito":"Aco"},
	                                                                {"id":2,"distrito":"Bambas"},
	                                                                {"id":3,"distrito":"Cusca"},
	                                                                {"id":4,"distrito":"La Pampa"},
	                                                                {"id":5,"distrito":"Yanac"},
	                                                                {"id":6,"distrito":"Yupan"}
	                                     ]},
	                                     {"id":9,"provincia":"Huari","distritos":[
	                                                                {"id":0,"distrito":"Huari"},
	                                                                {"id":1,"distrito":"Anra"},
	                                                                {"id":2,"distrito":"Cajay"},
	                                                                {"id":3,"distrito":"Chavin de Huantar"},
	                                                                {"id":4,"distrito":"Huacachi"},
	                                                                {"id":5,"distrito":"Huacchis"},
	                                                                {"id":6,"distrito":"Huachis"},
	                                                                {"id":7,"distrito":"Huantar"},
	                                                                {"id":8,"distrito":"Masin"},
	                                                                {"id":9,"distrito":"Paucas"},
	                                                                {"id":10,"distrito":"Ponto"},
	                                                                {"id":11,"distrito":"Rahuapampa"},
	                                                                {"id":12,"distrito":"Rapayan"},
	                                                                {"id":13,"distrito":"San Marcos"},
	                                                                {"id":14,"distrito":"San Pedro de Chana"},
	                                                                {"id":15,"distrito":"Uco"}
	                                     ]},
	                                     {"id":10,"provincia":"Huarmey","distritos":[
	                                                                {"id":0,"distrito":"Huarmey"},
	                                                                {"id":1,"distrito":"Cochapeti"},
	                                                                {"id":2,"distrito":"Culebras"},
	                                                                {"id":3,"distrito":"Huayan"},
	                                                                {"id":4,"distrito":"Malvas"}
	                                     ]},
	                                     {"id":11,"provincia":"Huaylas","distritos":[
	                                                                {"id":0,"distrito":"Caraz"},
	                                                                {"id":1,"distrito":"Huallanca"},
	                                                                {"id":2,"distrito":"Huata"},
	                                                                {"id":3,"distrito":"Huaylas"},
	                                                                {"id":4,"distrito":"Mato"},
	                                                                {"id":5,"distrito":"Pamparomas"},
	                                                                {"id":6,"distrito":"Pueblo Libre"},
	                                                                {"id":7,"distrito":"Santa Cruz"},
	                                                                {"id":8,"distrito":"Santo Toribio"},
	                                                                {"id":9,"distrito":"Yuracmarca"}
	                                     ]},
	                                     {"id":12,"provincia":"Mariscal Luzuriaga","distritos":[
	                                                                {"id":0,"distrito":"Piscobamba"},
	                                                                {"id":1,"distrito":"Casca"},
	                                                                {"id":2,"distrito":"Eleazar Guzmán Barron"},
	                                                                {"id":3,"distrito":"Fidel Olivas Escudero"},
	                                                                {"id":4,"distrito":"Llama"},
	                                                                {"id":5,"distrito":"Llumpa"},
	                                                                {"id":6,"distrito":"Lucma"},
	                                                                {"id":7,"distrito":"Musga"}
	                                     ]},
	                                     {"id":13,"provincia":"Ocros","distritos":[
	                                                                {"id":0,"distrito":"Ocros"},
	                                                                {"id":1,"distrito":"Acas"},
	                                                                {"id":2,"distrito":"Cajamarquilla"},
	                                                                {"id":3,"distrito":"Carhuapampa"},
	                                                                {"id":4,"distrito":"Cochas"},
	                                                                {"id":5,"distrito":"Congas"},
	                                                                {"id":6,"distrito":"Llipa"},
	                                                                {"id":7,"distrito":"San Cristóbal de Rajan"},
	                                                                {"id":8,"distrito":"San Pedro"},
	                                                                {"id":9,"distrito":"Santiago de Chilcas"}
	                                     ]},
	                                     {"id":14,"provincia":"Pallasca","distritos":[
	                                                                {"id":0,"distrito":"Cabana"},
	                                                                {"id":1,"distrito":"Bolognesi"},
	                                                                {"id":2,"distrito":"Conchucos"},
	                                                                {"id":3,"distrito":"Huacaschuque"},
	                                                                {"id":4,"distrito":"Huandoval"},
	                                                                {"id":5,"distrito":"Lacabamba"},
	                                                                {"id":6,"distrito":"Llapos"},
	                                                                {"id":7,"distrito":"Pallasca"},
	                                                                {"id":8,"distrito":"Pampas"},
	                                                                {"id":9,"distrito":"Santa Rosa"},
	                                                                {"id":10,"distrito":"Tauca"}
	                                     ]},
	                                     {"id":15,"provincia":"Pomabamba","distritos":[
	                                                                {"id":0,"distrito":"Pomabamba"},
	                                                                {"id":1,"distrito":"Huayllan"},
	                                                                {"id":2,"distrito":"Parobamba"},
	                                                                {"id":3,"distrito":"Quinuabamba"}
	                                     ]},
	                                     {"id":16,"provincia":"Recuay","distritos":[
	                                                                {"id":0,"distrito":"Recuay"},
	                                                                {"id":1,"distrito":"Catac"},
	                                                                {"id":2,"distrito":"Cotaparaco"},
	                                                                {"id":3,"distrito":"Huayllapampa"},
	                                                                {"id":4,"distrito":"Llacllin"},
	                                                                {"id":5,"distrito":"Marca"},
	                                                                {"id":6,"distrito":"Pampas Chico"},
	                                                                {"id":7,"distrito":"Pararin"},
	                                                                {"id":8,"distrito":"Tapacocha"},
	                                                                {"id":9,"distrito":"Ticapampa"}
	                                     ]},
	                                     {"id":17,"provincia":"Santa","distritos":[
	                                                                {"id":0,"distrito":"Chimbote"},
	                                                                {"id":1,"distrito":"Cáceres del Perú"},
	                                                                {"id":2,"distrito":"Coishco"},
	                                                                {"id":3,"distrito":"Macate"},
	                                                                {"id":4,"distrito":"Moro"},
	                                                                {"id":5,"distrito":"Nepeña"},
	                                                                {"id":6,"distrito":"Samanco"},
	                                                                {"id":7,"distrito":"Santa"},
	                                                                {"id":8,"distrito":"Nuevo Chimbote"}
	                                     ]},
	                                     {"id":18,"provincia":"Sihuas","distritos":[
	                                                                {"id":0,"distrito":"Sihuas"},
	                                                                {"id":1,"distrito":"Acobamba"},
	                                                                {"id":2,"distrito":"Alfonso Ugarte"},
	                                                                {"id":3,"distrito":"Cashapampa"},
	                                                                {"id":4,"distrito":"Chingalpo"},
	                                                                {"id":5,"distrito":"Huayllabamba"},
	                                                                {"id":6,"distrito":"Quiches"},
	                                                                {"id":7,"distrito":"Ragash"},
	                                                                {"id":8,"distrito":"San Juan"},
	                                                                {"id":9,"distrito":"Sicsibamba"}
	                                     ]},
	                                     {"id":19,"provincia":"Yungay","distritos":[
	                                                                {"id":0,"distrito":"Yungay"},
	                                                                {"id":1,"distrito":"Cascapara"},
	                                                                {"id":2,"distrito":"Mancos"},
	                                                                {"id":3,"distrito":"Matacoto"},
	                                                                {"id":4,"distrito":"Quillo"},
	                                                                {"id":5,"distrito":"Ranrahirca"},
	                                                                {"id":6,"distrito":"Shupluy"},
	                                                                {"id":7,"distrito":"Yanama"}
	                                     ]}
	    ]},
	    {"id":2,"departamento":"Apurimac","provincias":[
	                                     {"id":0,"provincia":"Abancay","distritos":[
                                                                    {"id":0,"distrito":"Abancay"},
	                                                                {"id":1,"distrito":"Chacoche"},
	                                                                {"id":2,"distrito":"Circa"},
	                                                                {"id":3,"distrito":"Curahuasi"},
	                                                                {"id":4,"distrito":"Huanipaca"},
	                                                                {"id":5,"distrito":"Lambrama"},
	                                                                {"id":6,"distrito":"Pichirhua"},
	                                                                {"id":7,"distrito":"San Pedro de Cachora"},
	                                                                {"id":8,"distrito":"Tamburco"}
	                                     ]},
	                                     {"id":1,"provincia":"Andahuaylas","distritos":[
	                                                                {"id":0,"distrito":"Andahuaylas"},
	                                                                {"id":1,"distrito":"Andarapa"},
	                                                                {"id":2,"distrito":"Chiara"},
	                                                                {"id":3,"distrito":"Huancarama"},
	                                                                {"id":4,"distrito":"Huancaray"},
	                                                                {"id":5,"distrito":"Huayana"},
	                                                                {"id":6,"distrito":"Kishuara"},
	                                                                {"id":7,"distrito":"Pacobamba"},
	                                                                {"id":8,"distrito":"Pacucha"},
	                                                                {"id":9,"distrito":"Pampachiri"},
	                                                                {"id":10,"distrito":"Pomacocha"},
	                                                                {"id":11,"distrito":"San Antonio de Cachi"},
	                                                                {"id":12,"distrito":"San Jerónimo"},
	                                                                {"id":13,"distrito":"San Miguel de Chaccrampa"},
	                                                                {"id":14,"distrito":"Santa María de Chicmo"},
	                                                                {"id":15,"distrito":"Talavera"},
	                                                                {"id":16,"distrito":"Tumay Huaraca"},
	                                                                {"id":17,"distrito":"Turpo"},
	                                                                {"id":18,"distrito":"Kaquiabamba"},
	                                                                {"id":19,"distrito":"José María Arguedas"}
	                                     ]},
	                                     {"id":2,"provincia":"Antabamba","distritos":[
	                                                                {"id":0,"distrito":"Antabamba"},
	                                                                {"id":1,"distrito":"El Oro"},
	                                                                {"id":2,"distrito":"Huaquirca"},
	                                                                {"id":3,"distrito":"Juan Espinoza Medrano"},
	                                                                {"id":4,"distrito":"Oropesa"},
	                                                                {"id":5,"distrito":"Pachaconas"},
	                                                                {"id":6,"distrito":"Sabaino"}
	                                     ]},
	                                     {"id":3,"provincia":"Aymaraes","distritos":[
	                                                                {"id":0,"distrito":"Chalhuanca"},
	                                                                {"id":1,"distrito":"Capaya"},
	                                                                {"id":2,"distrito":"Caraybamba"},
	                                                                {"id":3,"distrito":"Chapimarca"},
	                                                                {"id":4,"distrito":"Colcabamba"},
	                                                                {"id":5,"distrito":"Cotaruse"},
	                                                                {"id":6,"distrito":"Ihuayllo"},
	                                                                {"id":7,"distrito":"Justo Apu Sahuaraura"},
	                                                                {"id":8,"distrito":"Lucre"},
	                                                                {"id":9,"distrito":"Pocohuanca"},
	                                                                {"id":10,"distrito":"San Juan de Chacña"},
	                                                                {"id":11,"distrito":"Sañayca"},
	                                                                {"id":12,"distrito":"Soraya"},
	                                                                {"id":13,"distrito":"Tapairihua"},
	                                                                {"id":14,"distrito":"Tintay"},
	                                                                {"id":15,"distrito":"Toraya"},
	                                                                {"id":16,"distrito":"Yanaca"}
	                                     ]},
	                                     {"id":4,"provincia":"Cotabambas","distritos":[
	                                                                {"id":0,"distrito":"Tambobamba"},
	                                                                {"id":1,"distrito":"Cotabambas"},
	                                                                {"id":2,"distrito":"Coyllurqui"},
	                                                                {"id":3,"distrito":"Haquira"},
	                                                                {"id":4,"distrito":"Mara"},
	                                                                {"id":5,"distrito":"Challhuahuacho"}
	                                     ]},
	                                     {"id":5,"provincia":"Chincheros","distritos":[
	                                                                {"id":0,"distrito":"Chincheros"},
	                                                                {"id":1,"distrito":"Anco Huallo"},
	                                                                {"id":2,"distrito":"Cocharcas"},
	                                                                {"id":3,"distrito":"Huaccana"},
	                                                                {"id":4,"distrito":"Ocobamba"},
	                                                                {"id":5,"distrito":"Ongoy"},
	                                                                {"id":6,"distrito":"Uranmarca"},
	                                                                {"id":7,"distrito":"Ranracancha"},
	                                                                {"id":8,"distrito":"Rocchacc"},
	                                                                {"id":9,"distrito":"El Porvenir"},
	                                                                {"id":10,"distrito":"Los Chankas"}
	                                     ]},
	                                     {"id":6,"provincia":"Grau","distritos":[
	                                                                {"id":0,"distrito":"Chuquibambilla"},
	                                                                {"id":1,"distrito":"Curpahuasi"},
	                                                                {"id":2,"distrito":"Gamarra"},
	                                                                {"id":3,"distrito":"Huayllati"},
	                                                                {"id":4,"distrito":"Mamara"},
	                                                                {"id":5,"distrito":"Micaela Bastidas"},
	                                                                {"id":6,"distrito":"Pataypampa"},
	                                                                {"id":7,"distrito":"Progreso"},
	                                                                {"id":8,"distrito":"San Antonio"},
	                                                                {"id":9,"distrito":"Santa Rosa"},
	                                                                {"id":10,"distrito":"Turpay"},
	                                                                {"id":11,"distrito":"Vilcabamba"},
	                                                                {"id":12,"distrito":"Virundo"},
	                                                                {"id":13,"distrito":"Curasco"}
	                                     ]}
	    ]},
	    {"id":3,"departamento":"Arequipa","provincias":[
	                                     {"id":0,"provincia":"Arequipa","distritos":[
	                                                                {"id":0,"distrito":"Arequipa"},
	                                                                {"id":1,"distrito":"Alto Selva Alegre"},
	                                                                {"id":2,"distrito":"Cayma"},
	                                                                {"id":3,"distrito":"Cerro Colorado"},
	                                                                {"id":4,"distrito":"Characato"},
	                                                                {"id":5,"distrito":"Chiguata"},
	                                                                {"id":6,"distrito":"Jacobo Hunter"},
	                                                                {"id":7,"distrito":"La Joya"},
	                                                                {"id":8,"distrito":"Mariano Melgar"},
	                                                                {"id":9,"distrito":"Miraflores"},
	                                                                {"id":10,"distrito":"Mollebaya"},
	                                                                {"id":11,"distrito":"Paucarpata"},
	                                                                {"id":12,"distrito":"Pocsi"},
	                                                                {"id":13,"distrito":"Polobaya"},
	                                                                {"id":14,"distrito":"Quequeña"},
	                                                                {"id":15,"distrito":"Sabandia"},
	                                                                {"id":16,"distrito":"Sachaca"},
	                                                                {"id":17,"distrito":"San Juan de Siguas"},
	                                                                {"id":18,"distrito":"San Juan de Tarucani"},
	                                                                {"id":19,"distrito":"Santa Isabel de Siguas"},
	                                                                {"id":20,"distrito":"Santa Rita de Siguas"},
	                                                                {"id":21,"distrito":"Socabaya"},
	                                                                {"id":22,"distrito":"Tiabaya"},
	                                                                {"id":23,"distrito":"Uchumayo"},
	                                                                {"id":24,"distrito":"Vitor"},
	                                                                {"id":25,"distrito":"Yanahuara"},
	                                                                {"id":26,"distrito":"Yarabamba"},
	                                                                {"id":27,"distrito":"Yura"},
	                                                                {"id":28,"distrito":"José Luis Bustamante y Rivero"}
	                                     ]},
	                                     {"id":1,"provincia":"Camaná","distritos":[
	                                                                {"id":0,"distrito":"Camaná"},
	                                                                {"id":1,"distrito":"José María Quimpere"},
	                                                                {"id":2,"distrito":"Mariano Nicolás Valcárcel"},
	                                                                {"id":3,"distrito":"Mariscal Cáceres"},
	                                                                {"id":4,"distrito":"Nicolás de Pierola"},
	                                                                {"id":5,"distrito":"Ocoña"},
	                                                                {"id":6,"distrito":"Quilca"},
	                                                                {"id":7,"distrito":"Samuel Pastor"}
	                                     ]},
	                                     {"id":2,"provincia":"Caravelí","distritos":[
	                                                                {"id":0,"distrito":"Caravelí"},
	                                                                {"id":1,"distrito":"Acarí"},
	                                                                {"id":2,"distrito":"Atico"},
	                                                                {"id":3,"distrito":"Atiquipa"},
	                                                                {"id":4,"distrito":"Bella Unión"},
	                                                                {"id":5,"distrito":"Cahuacho"},
	                                                                {"id":6,"distrito":"Chala"},
	                                                                {"id":7,"distrito":"Chaparra"},
	                                                                {"id":8,"distrito":"Huanuhuanu"},
	                                                                {"id":9,"distrito":"Jaqui"},
	                                                                {"id":10,"distrito":"Lomas"},
	                                                                {"id":11,"distrito":"Quicacha"},
	                                                                {"id":12,"distrito":"Yauca"}
	                                     ]},
	                                     {"id":3,"provincia":"Castilla","distritos":[
	                                                                {"id":0,"distrito":"Aplao"},
	                                                                {"id":1,"distrito":"Andagua"},
	                                                                {"id":2,"distrito":"Ayo"},
	                                                                {"id":3,"distrito":"Chachas"},
	                                                                {"id":4,"distrito":"Chilcaymarca"},
	                                                                {"id":5,"distrito":"Choco"},
	                                                                {"id":6,"distrito":"Huancarqui"},
	                                                                {"id":7,"distrito":"Machaguay"},
	                                                                {"id":8,"distrito":"Orcopampa"},
	                                                                {"id":9,"distrito":"Pampacolca"},
	                                                                {"id":10,"distrito":"Tipan"},
	                                                                {"id":11,"distrito":"Uñon"},
	                                                                {"id":12,"distrito":"Uraca"},
	                                                                {"id":13,"distrito":"Viraco"}
	                                     ]},
	                                     {"id":4,"provincia":"Caylloma","distritos":[
	                                                                {"id":0,"distrito":"Chivay"},
	                                                                {"id":1,"distrito":"Achoma"},
	                                                                {"id":2,"distrito":"Cabanaconde"},
	                                                                {"id":3,"distrito":"Callalli"},
	                                                                {"id":4,"distrito":"Caylloma"},
	                                                                {"id":5,"distrito":"Coporaque"},
	                                                                {"id":6,"distrito":"Huambo"},
	                                                                {"id":7,"distrito":"Huanca"},
	                                                                {"id":8,"distrito":"Ichupampa"},
	                                                                {"id":9,"distrito":"Lari"},
	                                                                {"id":10,"distrito":"Lluta"},
	                                                                {"id":11,"distrito":"Maca"},
	                                                                {"id":12,"distrito":"Madrigal"},
	                                                                {"id":13,"distrito":"San Antonio de Chuca"},
	                                                                {"id":14,"distrito":"Sibayo"},
	                                                                {"id":15,"distrito":"Tapay"},
	                                                                {"id":16,"distrito":"Tisco"},
	                                                                {"id":17,"distrito":"Tuti"},
	                                                                {"id":18,"distrito":"Yanque"},
	                                                                {"id":19,"distrito":"Majes"}
	                                     ]},
	                                     {"id":5,"provincia":"Condesuyos","distritos":[
	                                                                {"id":0,"distrito":"Chuquibamba"},
	                                                                {"id":1,"distrito":"Andaray"},
	                                                                {"id":2,"distrito":"Cayarani"},
	                                                                {"id":3,"distrito":"Chichas"},
	                                                                {"id":4,"distrito":"Iray"},
	                                                                {"id":5,"distrito":"Río Grande"},
	                                                                {"id":6,"distrito":"Salamanca"},
	                                                                {"id":7,"distrito":"Yanaquihua"}
	                                     ]},
	                                     {"id":6,"provincia":"Islay","distritos":[
	                                                                {"id":0,"distrito":"Mollendo"},
	                                                                {"id":1,"distrito":"Cocachacra"},
	                                                                {"id":2,"distrito":"Dean Valdivia"},
	                                                                {"id":3,"distrito":"Islay"},
	                                                                {"id":4,"distrito":"Mejia"},
	                                                                {"id":5,"distrito":"Punta de Bombón"}
	                                     ]},
	                                     {"id":7,"provincia":"La Unión","distritos":[             
                                                                    {"id":0,"distrito":"Cotahuasi"},
	                                                                {"id":1,"distrito":"Alca"},
	                                                                {"id":2,"distrito":"Charcana"},
	                                                                {"id":3,"distrito":"Huaynacotas"},
	                                                                {"id":4,"distrito":"Pampamarca"},
	                                                                {"id":5,"distrito":"Puyca"},
	                                                                {"id":6,"distrito":"Quechualla"},
	                                                                {"id":7,"distrito":"Sayla"},
	                                                                {"id":8,"distrito":"Tauria"},
	                                                                {"id":9,"distrito":"Tomepampa"},
	                                                                {"id":10,"distrito":"Toro"}
	                                     ]}
	    ]},
	    {"id":4,"departamento":"Ayacucho","provincias":[
	                                     {"id":0,"provincia":"Huamanga","distritos":[
	                                                                {"id":0,"distrito":"Ayacucho"},
	                                                                {"id":1,"distrito":"Acocro"},
	                                                                {"id":2,"distrito":"Acos Vinchos"},
	                                                                {"id":3,"distrito":"Carmen Alto"},
	                                                                {"id":4,"distrito":"Chiara"},
	                                                                {"id":5,"distrito":"Ocros"},
	                                                                {"id":6,"distrito":"Pacaycasa"},
	                                                                {"id":7,"distrito":"Quinua"},
	                                                                {"id":8,"distrito":"San José de Ticllas"},
	                                                                {"id":9,"distrito":"San Juan Bautista"},
	                                                                {"id":10,"distrito":"Santiago de Pischa"},
	                                                                {"id":11,"distrito":"Socos"},
	                                                                {"id":12,"distrito":"Tambillo"},
	                                                                {"id":13,"distrito":"Vinchos"},
	                                                                {"id":14,"distrito":"Jesús Nazareno"},
	                                                                {"id":15,"distrito":"Andrés Avelino Cáceres Dorregaray"}
	                                     ]},
	                                     {"id":1,"provincia":"Cangallo","distritos":[
	                                                                {"id":0,"distrito":"Cangallo"},
	                                                                {"id":1,"distrito":"Chuschi"},
	                                                                {"id":2,"distrito":"Los Morochucos"},
	                                                                {"id":3,"distrito":"María Parado de Bellido"},
	                                                                {"id":4,"distrito":"Paras"},
	                                                                {"id":5,"distrito":"Totos"}
	                                     ]},
	                                     {"id":2,"provincia":"Huanca Sancos","distritos":[
	                                                                {"id":0,"distrito":"Sancos"},
	                                                                {"id":1,"distrito":"Carapo"},
	                                                                {"id":2,"distrito":"Sacsamarca"},
	                                                                {"id":3,"distrito":"Santiago de Lucanamarca"}
	                                     ]},
	                                     {"id":3,"provincia":"Huanta","distritos":[
	                                                                {"id":0,"distrito":"Huanta"},
	                                                                {"id":1,"distrito":"Ayahuanco"},
	                                                                {"id":2,"distrito":"Huamanguilla"},
	                                                                {"id":3,"distrito":"Iguain"},
	                                                                {"id":4,"distrito":"Luricocha"},
	                                                                {"id":5,"distrito":"Santillana"},
	                                                                {"id":6,"distrito":"Sivia"},
	                                                                {"id":7,"distrito":"Llochegua"},
	                                                                {"id":8,"distrito":"Canayre"},
	                                                                {"id":9,"distrito":"Uchuraccay"},
	                                                                {"id":10,"distrito":"Pucacolpa"},
	                                                                {"id":11,"distrito":"Chaca"}
	                                     ]},
	                                     {"id":4,"provincia":"La Mar","distritos":[
	                                                                {"id":0,"distrito":"San Miguel"},
	                                                                {"id":1,"distrito":"Anco"},
	                                                                {"id":2,"distrito":"Ayna"},
	                                                                {"id":3,"distrito":"Chilcas"},
	                                                                {"id":4,"distrito":"Chungui"},
	                                                                {"id":5,"distrito":"Luis Carranza"},
	                                                                {"id":6,"distrito":"Santa Rosa"},
	                                                                {"id":7,"distrito":"Tambo"},
	                                                                {"id":8,"distrito":"Samugari"},
	                                                                {"id":9,"distrito":"Anchihuay"},
	                                                                {"id":10,"distrito":"Oronccoy"}
	                                     ]},
	                                     {"id":5,"provincia":"Lucanas","distritos":[
	                                                                {"id":0,"distrito":"Puquio"},
	                                                                {"id":1,"distrito":"Aucara"},
	                                                                {"id":2,"distrito":"Cabana"},
	                                                                {"id":3,"distrito":"Carmen Salcedo"},
	                                                                {"id":4,"distrito":"Chaviña"},
	                                                                {"id":5,"distrito":"Chipao"},
	                                                                {"id":6,"distrito":"Huac-Huas"},
	                                                                {"id":7,"distrito":"Laramate"},
	                                                                {"id":8,"distrito":"Leoncio Prado"},
	                                                                {"id":9,"distrito":"Llauta"},
	                                                                {"id":10,"distrito":"Lucanas"},
	                                                                {"id":11,"distrito":"Ocaña"},
	                                                                {"id":12,"distrito":"Otoca"},
	                                                                {"id":13,"distrito":"Saisa"},
	                                                                {"id":14,"distrito":"San Cristóbal"},
	                                                                {"id":15,"distrito":"San Juan"},
	                                                                {"id":16,"distrito":"San Pedro"},
	                                                                {"id":17,"distrito":"San Pedro de Palco"},
	                                                                {"id":18,"distrito":"Sancos"},
	                                                                {"id":19,"distrito":"Santa Ana de Huaycahuacho"},
	                                                                {"id":20,"distrito":"Santa Lucia"}
	                                     ]},
	                                     {"id":6,"provincia":"Parinacochas","distritos":[
	                                                                {"id":0,"distrito":"Coracora"},
	                                                                {"id":1,"distrito":"Chumpi"},
	                                                                {"id":2,"distrito":"Coronel Castañeda"},
	                                                                {"id":3,"distrito":"Pacapausa"},
	                                                                {"id":4,"distrito":"Pullo"},
	                                                                {"id":5,"distrito":"Puyusca"},
	                                                                {"id":6,"distrito":"San Francisco de Ravacayco"},
	                                                                {"id":7,"distrito":"Upahuacho"}
	                                     ]},
	                                     {"id":7,"provincia":"Páucar del Sara Sara","distritos":[
	                                                                {"id":0,"distrito":"Pausa"},
	                                                                {"id":1,"distrito":"Colta"},
	                                                                {"id":2,"distrito":"Corculla"},
	                                                                {"id":3,"distrito":"Lampa"},
	                                                                {"id":4,"distrito":"Marcabamba"},
	                                                                {"id":5,"distrito":"Oyolo"},
	                                                                {"id":6,"distrito":"Pararca"},
	                                                                {"id":7,"distrito":"San Javier de Alpabamba"},
	                                                                {"id":8,"distrito":"San José de Ushua"},
	                                                                {"id":9,"distrito":"Sara Sara"}
	                                     ]},
	                                     {"id":8,"provincia":"Sucre","distritos":[
	                                                                {"id":0,"distrito":"Querobamba"},
	                                                                {"id":1,"distrito":"Belén"},
	                                                                {"id":2,"distrito":"Chalcos"},
	                                                                {"id":3,"distrito":"Chilcayoc"},
	                                                                {"id":4,"distrito":"Huacaña"},
	                                                                {"id":5,"distrito":"Morcolla"},
	                                                                {"id":6,"distrito":"Paico"},
	                                                                {"id":7,"distrito":"San Pedro de Larcay"},
	                                                                {"id":8,"distrito":"San Salvador de Quije"},
	                                                                {"id":9,"distrito":"Santiago de Paucaray"},
	                                                                {"id":10,"distrito":"Soras"}
	                                     ]},
	                                     {"id":9,"provincia":"Víctor Fajardo","distritos":[
	                                                                {"id":0,"distrito":"Huancapi"},
	                                                                {"id":1,"distrito":"Alcamenca"},
	                                                                {"id":2,"distrito":"Apongo"},
	                                                                {"id":3,"distrito":"Asquipata"},
	                                                                {"id":4,"distrito":"Canaria"},
	                                                                {"id":5,"distrito":"Cayara"},
	                                                                {"id":6,"distrito":"Colca"},
	                                                                {"id":7,"distrito":"Huamanquiquia"},
	                                                                {"id":8,"distrito":"Huancaraylla"},
	                                                                {"id":9,"distrito":"Huaya"},
	                                                                {"id":10,"distrito":"Sarhua"},
	                                                                {"id":11,"distrito":"Vilcanchos"}
	                                     ]},
	                                     {"id":10,"provincia":"Vilcas Huamán","distritos":[
	                                                                {"id":0,"distrito":"Vilcas Huaman"},
	                                                                {"id":1,"distrito":"Accomarca"},
	                                                                {"id":2,"distrito":"Carhuanca"},
	                                                                {"id":3,"distrito":"Concepción"},
	                                                                {"id":4,"distrito":"Huambalpa"},
	                                                                {"id":5,"distrito":"Independencia"},
	                                                                {"id":6,"distrito":"Saurama"},
	                                                                {"id":7,"distrito":"Vischongo"}
	                                     ]}
        ]},
	    {"id":5,"departamento":"Cajamarca","provincias":[
	                                     {"id":0,"provincia":"Cajamarca"},
	                                     {"id":1,"provincia":"Cajabamba"},
	                                     {"id":2,"provincia":"Celendín"},
	                                     {"id":3,"provincia":"Chota"},
	                                     {"id":4,"provincia":"Contumazá"},
	                                     {"id":5,"provincia":"Cutervo"},
	                                     {"id":6,"provincia":"Hualgayoc"},
	                                     {"id":7,"provincia":"Jaén"},
	                                     {"id":8,"provincia":"San Ignacio"},
	                                     {"id":9,"provincia":"San Marcos"},
	                                     {"id":10,"provincia":"San Miguel"},
	                                     {"id":11,"provincia":"San Pablo"},
	                                     {"id":12,"provincia":"Santa Cruz"}
	    ]},
	    {"id":6,"departamento":"Callao","provincias":[
	                                     {"id":0,"provincia":"Prov. Const. del Callao"}
	    ]},
	    {"id":7,"departamento":"Cusco","provincias":[
	                                     {"id":0,"provincia":"Cusco"},
	                                     {"id":1,"provincia":"Acomayo"},
	                                     {"id":2,"provincia":"Anta"},
	                                     {"id":3,"provincia":"Calca"},
	                                     {"id":4,"provincia":"Canas"},
	                                     {"id":5,"provincia":"Canchis"},
	                                     {"id":6,"provincia":"Chumbivilcas"},
	                                     {"id":7,"provincia":"Espinar"},
	                                     {"id":8,"provincia":"La Convención"},
	                                     {"id":9,"provincia":"Paruro"},
	                                     {"id":10,"provincia":"Paucartambo"},
	                                     {"id":11,"provincia":"Quispicanchi"},
	                                     {"id":12,"provincia":"Urubamba"}
	    ]},
	    {"id":8,"departamento":"Huancavelica","provincias":[
	                                     {"id":0,"provincia":"Huancavelica"},
	                                     {"id":1,"provincia":"Acobamba"},
	                                     {"id":2,"provincia":"Angaraes"},
	                                     {"id":3,"provincia":"Castrovirreyna"},
	                                     {"id":4,"provincia":"Churcampa"},
	                                     {"id":5,"provincia":"Huaytará"},
	                                     {"id":6,"provincia":"Tayacaja"}
	    ]},
	    {"id":9,"departamento":"Huánuco","provincias":[
	                                     {"id":0,"provincia":"Huánuco"},
	                                     {"id":1,"provincia":"Ambo"},
	                                     {"id":2,"provincia":"Dos de Mayo"},
	                                     {"id":3,"provincia":"Huacaybamba"},
	                                     {"id":4,"provincia":"Huamalíes"},
	                                     {"id":5,"provincia":"Leoncio Prado"},
	                                     {"id":6,"provincia":"Marañón"},
	                                     {"id":7,"provincia":"Pachitea"},
	                                     {"id":8,"provincia":"Puerto Inca"},
	                                     {"id":9,"provincia":"Lauricocha"},
	                                     {"id":10,"provincia":"Yarowilca"}
	    ]},
	    {"id":10,"departamento":"Ica","provincias":[
	                                     {"id":0,"provincia":"Ica"},
	                                     {"id":1,"provincia":"Chincha"},
	                                     {"id":2,"provincia":"Nasca"},
	                                     {"id":3,"provincia":"Palpa"},
	                                     {"id":4,"provincia":"Pisco"}
	    ]},
	    {"id":11,"departamento":"Junín","provincias":[
	                                     {"id":0,"provincia":"Huancayo"},
	                                     {"id":1,"provincia":"Concepción"},
	                                     {"id":2,"provincia":"Chanchamayo"},
	                                     {"id":3,"provincia":"Jauja"},
	                                     {"id":4,"provincia":"Junín"},
	                                     {"id":5,"provincia":"Satipo"},
	                                     {"id":6,"provincia":"Tarma"},
	                                     {"id":7,"provincia":"Yauli"},
	                                     {"id":8,"provincia":"Chupaca"}
	    ]},
		{"id":12,"departamento":"La Libertad","provincias":[
		                                 {"id":0,"provincia":"Trujillo"},
	                                     {"id":1,"provincia":"Ascope"},
	                                     {"id":2,"provincia":"Bolívar"},
	                                     {"id":3,"provincia":"Chepén"},
	                                     {"id":4,"provincia":"Julcán"},
	                                     {"id":5,"provincia":"Otuzco"},
	                                     {"id":6,"provincia":"Pacasmayo"},
	                                     {"id":7,"provincia":"Pataz"},
	                                     {"id":8,"provincia":"Sánchez Carrión"},
	                                     {"id":9,"provincia":"Santiago de Chuco"},
	                                     {"id":10,"provincia":"Gran Chimú"},
	                                     {"id":11,"provincia":"Virú"}
		]},
		{"id":13,"departamento":"Lambayeque","provincias":[
		                                 {"id":0,"provincia":"Chiclayo"},
	                                     {"id":1,"provincia":"Ferreñafe"},
	                                     {"id":2,"provincia":"Lambayeque"}
		]},
		{"id":14,"departamento":"Lima","provincias":[
		                                 {"id":0,"provincia":"Lima"},
	                                     {"id":1,"provincia":"Barranca"},
	                                     {"id":2,"provincia":"Cajatambo"},
	                                     {"id":3,"provincia":"Canta"},
	                                     {"id":4,"provincia":"Cañete"},
	                                     {"id":5,"provincia":"Huaral"},
	                                     {"id":6,"provincia":"Huarochirí"},
	                                     {"id":7,"provincia":"Huaura"},
	                                     {"id":8,"provincia":"Oyón"},
	                                     {"id":9,"provincia":"Yauyos"}
		]},
        {"id":15,"departamento":"Loreto","provincias":[
                                         {"id":0,"provincia":"Maynas"},
	                                     {"id":1,"provincia":"Alto Amazonas"},
	                                     {"id":2,"provincia":"Loreto"},
	                                     {"id":3,"provincia":"Mariscal Ramón Castilla"},
	                                     {"id":4,"provincia":"Requena"},
	                                     {"id":5,"provincia":"Ucayali"},
	                                     {"id":6,"provincia":"Datem del Marañón"},
	                                     {"id":7,"provincia":"Putumayo"}
        ]},
		{"id":16,"departamento":"Madre de Dios","provincias":[
		                                 {"id":0,"provincia":"Tambopata"},
	                                     {"id":1,"provincia":"Manu"},
	                                     {"id":2,"provincia":"Tahuamanu"}
		]},
		{"id":17,"departamento":"Moquegua","provincias":[
		                                 {"id":0,"provincia":"Mariscal Nieto"},
	                                     {"id":1,"provincia":"General Sánchez Cerro"},
	                                     {"id":2,"provincia":"Ilo"}
		]},
		{"id":18,"departamento":"Pasco","provincias":[
		                                 {"id":0,"provincia":"Pasco"},
	                                     {"id":1,"provincia":"Daniel Alcides Carrión"},
	                                     {"id":2,"provincia":"Oxapampa"}
		]},
		{"id":19,"departamento":"Piura","provincias":[
		                                 {"id":0,"provincia":"Piura"},
	                                     {"id":1,"provincia":"Ayabaca"},
	                                     {"id":2,"provincia":"Huancabamba"},
	                                     {"id":3,"provincia":"Morropón"},
	                                     {"id":4,"provincia":"Paita"},
	                                     {"id":5,"provincia":"Sullana"},
	                                     {"id":6,"provincia":"Talara"},
	                                     {"id":7,"provincia":"Sechura"}
		]},
        {"id":20,"departamento":"Puno","provincias":[
                                         {"id":0,"provincia":"Puno"},
	                                     {"id":1,"provincia":"Azángaro"},
	                                     {"id":2,"provincia":"Carabaya"},
	                                     {"id":3,"provincia":"Chucuito"},
	                                     {"id":4,"provincia":"El Collao"},
	                                     {"id":5,"provincia":"Huancané"},
	                                     {"id":6,"provincia":"Lampa"},
	                                     {"id":7,"provincia":"Melgar"},
	                                     {"id":8,"provincia":"Moho"},
	                                     {"id":9,"provincia":"San Antonio de Putina"},
	                                     {"id":10,"provincia":"San Román"},
	                                     {"id":11,"provincia":"Sandia"},
	                                     {"id":12,"provincia":"Yunguyo"}
        ]},
		{"id":21,"departamento":"San Martín","provincias":[
		                                 {"id":0,"provincia":"Moyobamba"},
	                                     {"id":1,"provincia":"Bellavista"},
	                                     {"id":2,"provincia":"El Dorado"},
	                                     {"id":3,"provincia":"Huallaga"},
	                                     {"id":4,"provincia":"Lamas"},
	                                     {"id":5,"provincia":"Mariscal Cáceres"},
	                                     {"id":6,"provincia":"Picota"},
	                                     {"id":7,"provincia":"Rioja"},
	                                     {"id":8,"provincia":"San Martín"},
	                                     {"id":9,"provincia":"Tocache"}
		]},
		{"id":22,"departamento":"Tacna","provincias":[
		                                 {"id":0,"provincia":"Tacna"},
	                                     {"id":1,"provincia":"Candarave"},
	                                     {"id":2,"provincia":"Jorge Basadre"},
	                                     {"id":3,"provincia":"Tarata"}
		]},
		{"id":23,"departamento":"Tumbes","provincias":[
		                                 {"id":0,"provincia":"Tumbes"},
	                                     {"id":1,"provincia":"Contralmirante Villar"},
	                                     {"id":2,"provincia":"Zarumilla"}
		]},
		{"id":24,"departamento":"Ucayali","provincias":[
		                                 {"id":0,"provincia":"Coronel Portillo"},
	                                     {"id":1,"provincia":"Atalaya"},
	                                     {"id":2,"provincia":"Padre Abad"},
	                                     {"id":3,"provincia":"Purús"}
		]}
]}